asodesigner/LocusInfo.py
asodesigner/__init__.py
asodesigner/aso_generator.py
asodesigner/consts.py
asodesigner/consts_dataframe.py
asodesigner/data_handling.py
asodesigner/download_and_create_human_genome.py
asodesigner/download_assets.py
asodesigner/feature_creation.py
asodesigner/genome.py
asodesigner/genome_file_utils.py
asodesigner/model.json
asodesigner/process_utils.py
asodesigner/random_util.py
asodesigner/read_human_genome.py
asodesigner/run_pipe.py
asodesigner/timer.py
asodesigner/util.py
asodesigner/utils.py
asodesigner/algorithms/__init__.py
asodesigner/algorithms/suffix_array.py
asodesigner/features/RNaseH_features.py
asodesigner/features/__init__.py
asodesigner/features/cai.py
asodesigner/features/feature_names.py
asodesigner/features/hybridization.py
asodesigner/features/mod_features.py
asodesigner/features/seq_features.py
asodesigner/features/smart_hybridization.py
asodesigner/features/vienna_fold.py
asodesigner/features/rna_access/__init__.py
asodesigner/features/rna_access/access_calculator.py
asodesigner/features/rna_access/file_util.py
asodesigner/features/rna_access/rna_access.py
asodesigner/features/rna_access/sense_accessibility.py
asodesigner/features/rna_access/output/stub
asodesigner/hybridization/__init__.py
asodesigner/hybridization/exp_weights.py
asodesigner/hybridization/hybridization_features.py
asodesigner/hybridization/md_weights.py
asodesigner/off_target/aso_counts.py
asodesigner/off_target/cat.py
asodesigner/off_target/counter.py
asodesigner/off_target/find_matches_in_bam.py
asodesigner/populate/__init__.py
asodesigner/populate/populate_cai.py
asodesigner/populate/populate_sense_accessibility.py
asodesigner/populate/cai_cache/weights_cache.json
asodesigner-1.1.8.dist-info/licenses/LICENSE
asodesigner-1.1.8.dist-info/METADATA
asodesigner-1.1.8.dist-info/WHEEL
asodesigner-1.1.8.dist-info/top_level.txt
asodesigner-1.1.8.dist-info/RECORD
