Metadata-Version: 2.4
Name: asodesigner
Version: 1.1.8
Summary: Feature extraction and analysis toolkit for antisense oligonucleotide design.
Author: TAU-Israel iGEM Team
Project-URL: Homepage, https://2025.igem.wiki/tau-israel/home
Keywords: antisense,oligonucleotide,bioinformatics,igem
Classifier: Development Status :: 3 - Alpha
Classifier: Intended Audience :: Science/Research
Classifier: Programming Language :: Python :: 3
Classifier: Programming Language :: Python :: 3.9
Classifier: Programming Language :: Python :: 3.10
Classifier: Programming Language :: Python :: 3.11
Classifier: Programming Language :: Python :: 3.12
Classifier: Topic :: Scientific/Engineering :: Bio-Informatics
Requires-Python: <3.13,>=3.9
License-File: LICENSE
Requires-Dist: numpy<2.3,>=1.26
Requires-Dist: pandas<2.3,>=2.2
Requires-Dist: scipy<1.12,>=1.11
Requires-Dist: matplotlib
Requires-Dist: numba
Requires-Dist: biopython
Requires-Dist: ViennaRNA
Requires-Dist: primer3-py
Requires-Dist: gffutils
Requires-Dist: codon-bias
Requires-Dist: fuzzysearch
Requires-Dist: tqdm
Requires-Dist: multiprocess
Requires-Dist: gget
Requires-Dist: mega.py
Requires-Dist: xgboost>=2.0
Requires-Dist: scikit-learn>=1.5
Requires-Dist: gdown>=5.1.0
Requires-Dist: pysam
Dynamic: license-file
